vowcon_helper_code/__init__.py
vowcon_helper_code/df_utils.py
vowcon_helper_code/lecture.py
vowcon_removal_helper-0.1.1.dist-info/LICENSE
vowcon_removal_helper-0.1.1.dist-info/METADATA
vowcon_removal_helper-0.1.1.dist-info/WHEEL
vowcon_removal_helper-0.1.1.dist-info/top_level.txt
vowcon_removal_helper-0.1.1.dist-info/RECORD
