Metadata-Version: 2.1
Name: vowcon-removal-helper
Version: 0.1.1
Summary: a collection of data science helper functions
Home-page: https://github.com/ASinani/vowcon_removal_helper
Author: ASinani
License: UNKNOWN
Platform: UNKNOWN
Classifier: Programming Language :: Python :: 3
Classifier: License :: OSI Approved :: MIT License
Classifier: Operating System :: OS Independent
Requires-Python: >=3.5
Requires-Dist: numpy
Requires-Dist: pandas
